<?xml version="1.0" encoding="UTF-8"?>
<!DOCTYPE mapper PUBLIC "-//mybatis.org//DTD Mapper 3.0//EN" "http://mybatis.org/dtd/mybatis-3-mapper.dtd">
<mapper namespace="com.chinamobile.iot.lightapp.mysql.dao.ApplyMapperExt">
  <resultMap id="BaseResultMap" type="com.chinamobile.iot.lightapp.mysql.dto.ApplyUserDTO">
    <!--
      WARNING - @mbg.generated
      This element is automatically generated by MyBatis Generator, do not modify.
    -->
    <id column="apply_apply_id" jdbcType="INTEGER" property="applyId" />
    <result column="apply_apply_user" jdbcType="INTEGER" property="applyUser" />
    <result column="apply_inviter" jdbcType="INTEGER" property="inviter" />
    <result column="apply_cycle_id" jdbcType="INTEGER" property="cycleId" />
    <result column="apply_apply_type" jdbcType="INTEGER" property="applyType" />
    <result column="apply_result" jdbcType="INTEGER" property="result" />
    <result column="apply_apply_time" jdbcType="TIMESTAMP" property="applyTime" />
    <result column="nick_name" jdbcType="VARCHAR" property="nickName" />
    <result column="phone" jdbcType="VARCHAR" property="phone" />
    <result column="user_photo_id" jdbcType="INTEGER" property="userPhotoId" />
    <result column="work_cycle_name" jdbcType="VARCHAR" property="workCycleName" />
  </resultMap>
  <sql id="Example_Where_Clause">
    <!--
      WARNING - @mbg.generated
      This element is automatically generated by MyBatis Generator, do not modify.
    -->
    <where>
      <foreach collection="oredCriteria" item="criteria" separator="or">
        <if test="criteria.valid">
          <trim prefix="(" prefixOverrides="and" suffix=")">
            <foreach collection="criteria.criteria" item="criterion">
              <choose>
                <when test="criterion.noValue">
                  and ${criterion.condition}
                </when>
                <when test="criterion.singleValue">
                  and ${criterion.condition} #{criterion.value}
                </when>
                <when test="criterion.betweenValue">
                  and ${criterion.condition} #{criterion.value} and #{criterion.secondValue}
                </when>
                <when test="criterion.listValue">
                  and ${criterion.condition}
                  <foreach close=")" collection="criterion.value" item="listItem" open="(" separator=",">
                    #{listItem}
                  </foreach>
                </when>
              </choose>
            </foreach>
          </trim>
        </if>
      </foreach>
    </where>
  </sql>
  <sql id="Update_By_Example_Where_Clause">
    <!--
      WARNING - @mbg.generated
      This element is automatically generated by MyBatis Generator, do not modify.
    -->
    <where>
      <foreach collection="example.oredCriteria" item="criteria" separator="or">
        <if test="criteria.valid">
          <trim prefix="(" prefixOverrides="and" suffix=")">
            <foreach collection="criteria.criteria" item="criterion">
              <choose>
                <when test="criterion.noValue">
                  and ${criterion.condition}
                </when>
                <when test="criterion.singleValue">
                  and ${criterion.condition} #{criterion.value}
                </when>
                <when test="criterion.betweenValue">
                  and ${criterion.condition} #{criterion.value} and #{criterion.secondValue}
                </when>
                <when test="criterion.listValue">
                  and ${criterion.condition}
                  <foreach close=")" collection="criterion.value" item="listItem" open="(" separator=",">
                    #{listItem}
                  </foreach>
                </when>
              </choose>
            </foreach>
          </trim>
        </if>
      </foreach>
    </where>
  </sql>
  <sql id="Base_Column_List">
    <!--
      WARNING - @mbg.generated
      This element is automatically generated by MyBatis Generator, do not modify.
    -->
    apply.apply_id as apply_apply_id, apply.apply_user as apply_apply_user, apply.inviter as apply_inviter, 
    apply.cycle_id as apply_cycle_id, apply.apply_type as apply_apply_type, apply.`result` as `apply_result`, 
    apply.apply_time as apply_apply_time, nick_name, phone,user.photo_id as user_photo_id,work_cycle_name
  </sql>
  <select id="selectByExample" parameterType="com.chinamobile.iot.lightapp.mysql.model.ApplyExample" resultMap="BaseResultMap">
    <!--
      WARNING - @mbg.generated
      This element is automatically generated by MyBatis Generator, do not modify.
    -->
    select
    <if test="distinct">
      distinct
    </if>
    'true' as QUERYID,
    <include refid="Base_Column_List" />
    from apply apply LEFT JOIN user ON apply.apply_user = user.user_id LEFT JOIN work_cycle ON apply.cycle_id = work_cycle.work_cycle_id
    <if test="_parameter != null">
      <include refid="Example_Where_Clause" />
    </if>
    <if test="orderByClause != null">
      order by ${orderByClause}
    </if>
  </select>
</mapper>